<?xml version="1.0" encoding="UTF-8"?>
<con:testSuite id="e74e82e7-a296-4109-8a84-fc29de26d553" name="TestSuite CountryCurrency" xmlns:con="http://eviware.com/soapui/config"><con:settings/><con:runType>SEQUENTIAL</con:runType><con:testCase id="5e217e90-d4f8-4778-994c-2af574e2fcd6" failOnError="true" failTestCaseOnErrors="true" keepSession="false" maxResults="0" name="Positive" searchProperties="true"><con:settings/><con:testStep type="request" name="Alpha-2 Code (2letters)" id="f0d06741-60d8-483e-b0fe-712eba0dbb94"><con:settings/><con:config xsi:type="con:RequestStep" xmlns:xsi="http://www.w3.org/2001/XMLSchema-instance"><con:interface>CountryInfoServiceSoapBinding12</con:interface><con:operation>CountryCurrency</con:operation><con:request name="Alpha-2 Code (2letters)" id="c916a693-708d-40f4-9f43-dd1d999c668f"><con:settings><con:setting id="com.eviware.soapui.impl.wsdl.WsdlRequest@request-headers">&lt;xml-fragment/></con:setting></con:settings><con:encoding>UTF-8</con:encoding><con:endpoint>http://webservices.oorsprong.org/websamples.countryinfo/CountryInfoService.wso</con:endpoint><con:request><![CDATA[<soap:Envelope xmlns:soap="http://www.w3.org/2003/05/soap-envelope" xmlns:web="http://www.oorsprong.org/websamples.countryinfo">\r
   <soap:Header/>\r
   <soap:Body>\r
      <web:CountryCurrency>\r
         <web:sCountryISOCode>AF</web:sCountryISOCode>\r
      </web:CountryCurrency>\r
   </soap:Body>\r
</soap:Envelope>]]></con:request><con:assertion type="SOAP Response" id="f102e279-eed4-4c65-8899-045c0bb6db05"/><con:assertion type="Simple Contains" id="0221f632-f60a-4518-91a8-e44a57829f86" name="Contains"><con:configuration><token>AFA</token><ignoreCase>false</ignoreCase><useRegEx>false</useRegEx></con:configuration></con:assertion><con:assertion type="Invalid HTTP Status Codes" id="e79f7b0b-d010-4a9a-81c9-44a238e54198" name="Invalid HTTP Status Codes"><con:configuration><codes>200 OK</codes></con:configuration></con:assertion><con:assertion type="Response SLA Assertion" id="35f9a8d0-8933-4cc5-b94f-cfb04dba8357" name="Response SLA"><con:configuration><SLA>100</SLA></con:configuration></con:assertion><con:credentials><con:authType>No Authorization</con:authType></con:credentials><con:jmsConfig JMSDeliveryMode="PERSISTENT"/><con:jmsPropertyConfig/><con:wsaConfig mustUnderstand="NONE" version="200508"/><con:wsrmConfig version="1.2"/></con:request></con:config></con:testStep><con:testStep type="request" name="Alpha-3 Code (3letters)" id="3ccd2313-184a-45aa-9dab-4ed058dd49d0"><con:settings/><con:config xsi:type="con:RequestStep" xmlns:xsi="http://www.w3.org/2001/XMLSchema-instance"><con:interface>CountryInfoServiceSoapBinding12</con:interface><con:operation>CountryCurrency</con:operation><con:request name="Alpha-3 Code (3letters)" id="499e935e-bd41-4970-b035-6b2924059e69"><con:settings><con:setting id="com.eviware.soapui.impl.wsdl.WsdlRequest@request-headers">&lt;xml-fragment/></con:setting></con:settings><con:encoding>UTF-8</con:encoding><con:endpoint>http://webservices.oorsprong.org/websamples.countryinfo/CountryInfoService.wso</con:endpoint><con:request><![CDATA[<soap:Envelope xmlns:soap="http://www.w3.org/2003/05/soap-envelope" xmlns:web="http://www.oorsprong.org/websamples.countryinfo">\r
   <soap:Header/>\r
   <soap:Body>\r
      <web:CountryCurrency>\r
         <web:sCountryISOCode>AFG</web:sCountryISOCode>\r
      </web:CountryCurrency>\r
   </soap:Body>\r
</soap:Envelope>]]></con:request><con:assertion type="SOAP Response" id="6f01ab7a-e8da-4815-aa69-4e4e7ae248df"/><con:assertion type="Simple Contains" id="35382353-5aba-4978-b9ce-0f231e0bd73b" name="Contains"><con:configuration><token>Afghanis</token><ignoreCase>false</ignoreCase><useRegEx>false</useRegEx></con:configuration></con:assertion><con:assertion type="Invalid HTTP Status Codes" id="8822edce-20d1-42b6-82eb-764b7cdadcce" name="Invalid HTTP Status Codes"><con:configuration><codes>200 OK</codes></con:configuration></con:assertion><con:assertion type="Response SLA Assertion" id="f726a99f-2e93-4139-b5f8-62bedd538aca" name="Response SLA"><con:configuration><SLA>200</SLA></con:configuration></con:assertion><con:credentials><con:authType>No Authorization</con:authType></con:credentials><con:jmsConfig JMSDeliveryMode="PERSISTENT"/><con:jmsPropertyConfig/><con:wsaConfig mustUnderstand="NONE" version="200508"/><con:wsrmConfig version="1.2"/></con:request></con:config></con:testStep><con:properties/></con:testCase><con:testCase id="5cec1cf4-0936-4f99-b8ec-8e7459c4aec7" failOnError="true" failTestCaseOnErrors="true" keepSession="false" maxResults="0" name="Negative" searchProperties="true"><con:settings/><con:testStep type="request" name="ISOCode - invalid amount of characters" id="ed357084-5192-4153-9d46-847b3aa734a7"><con:settings/><con:config xsi:type="con:RequestStep" xmlns:xsi="http://www.w3.org/2001/XMLSchema-instance"><con:interface>CountryInfoServiceSoapBinding12</con:interface><con:operation>CountryCurrency</con:operation><con:request name="ISOCode - invalid amount of characters" id="ba7998c6-bacd-46a4-9102-707c551d4e4d"><con:settings><con:setting id="com.eviware.soapui.impl.wsdl.WsdlRequest@request-headers">&lt;xml-fragment/></con:setting></con:settings><con:encoding>UTF-8</con:encoding><con:endpoint>http://webservices.oorsprong.org/websamples.countryinfo/CountryInfoService.wso</con:endpoint><con:request><![CDATA[<soap:Envelope xmlns:soap="http://www.w3.org/2003/05/soap-envelope" xmlns:web="http://www.oorsprong.org/websamples.countryinfo">\r
   <soap:Header/>\r
   <soap:Body>\r
      <web:CountryCurrency>\r
         <web:sCountryISOCode>asdasdasdasdasdasd</web:sCountryISOCode>\r
      </web:CountryCurrency>\r
   </soap:Body>\r
</soap:Envelope>]]></con:request><con:assertion type="SOAP Response" id="72e7800f-543f-4a6e-82ae-383fa5989c19"/><con:assertion type="Simple Contains" id="15220061-3812-4710-ad31-520c81dd28fd" name="Contains"><con:configuration><token/><ignoreCase>false</ignoreCase><useRegEx>false</useRegEx></con:configuration></con:assertion><con:assertion type="Invalid HTTP Status Codes" id="4d11f7d7-6250-4e60-bbc6-30fbb1076d8a" name="Invalid HTTP Status Codes"><con:configuration><codes>200 OK</codes></con:configuration></con:assertion><con:assertion type="Response SLA Assertion" id="567f5426-3c09-4adb-a40b-aa32dc01d2f3" name="Response SLA"><con:configuration><SLA>150</SLA></con:configuration></con:assertion><con:credentials><con:authType>No Authorization</con:authType></con:credentials><con:jmsConfig JMSDeliveryMode="PERSISTENT"/><con:jmsPropertyConfig/><con:wsaConfig mustUnderstand="NONE" version="200508"/><con:wsrmConfig version="1.2"/></con:request></con:config></con:testStep><con:testStep type="request" name="ISOCode - Chinese characters" id="7d2a0254-6ba8-43fb-a21f-22896d7b3206"><con:settings/><con:config xsi:type="con:RequestStep" xmlns:xsi="http://www.w3.org/2001/XMLSchema-instance"><con:interface>CountryInfoServiceSoapBinding12</con:interface><con:operation>CountryCurrency</con:operation><con:request name="ISOCode - Chinese characters" id="80b97bab-54f4-4e40-a82a-773f624af9b9"><con:settings><con:setting id="com.eviware.soapui.impl.wsdl.WsdlRequest@request-headers">&lt;xml-fragment/></con:setting></con:settings><con:encoding>UTF-8</con:encoding><con:endpoint>http://webservices.oorsprong.org/websamples.countryinfo/CountryInfoService.wso</con:endpoint><con:request><![CDATA[<soap:Envelope xmlns:soap="http://www.w3.org/2003/05/soap-envelope" xmlns:web="http://www.oorsprong.org/websamples.countryinfo">\r
   <soap:Header/>\r
   <soap:Body>\r
      <web:CountryCurrency>\r
         <web:sCountryISOCode>天上太阳红衫衫</web:sCountryISOCode>\r
      </web:CountryCurrency>\r
   </soap:Body>\r
</soap:Envelope>]]></con:request><con:assertion type="SOAP Response" id="f4a0fa75-e129-4e61-85fd-26b1a24e9459"/><con:assertion type="Invalid HTTP Status Codes" id="90804f84-10f8-4d07-8749-4d7ac42dc7de" name="Invalid HTTP Status Codes"><con:configuration><codes>200 OK</codes></con:configuration></con:assertion><con:assertion type="Response SLA Assertion" id="156fddcc-d22c-44ec-8044-857a2532b1a9" name="Response SLA"><con:configuration><SLA>300</SLA></con:configuration></con:assertion><con:credentials><con:authType>No Authorization</con:authType></con:credentials><con:jmsConfig JMSDeliveryMode="PERSISTENT"/><con:jmsPropertyConfig/><con:wsaConfig mustUnderstand="NONE" version="200508"/><con:wsrmConfig version="1.2"/></con:request></con:config></con:testStep><con:properties/></con:testCase><con:properties/></con:testSuite>